simple_tg_md/__init__.py
simple_tg_md/main.py
simple_tg_md-0.1.1.dist-info/LICENSE
simple_tg_md-0.1.1.dist-info/METADATA
simple_tg_md-0.1.1.dist-info/WHEEL
simple_tg_md-0.1.1.dist-info/top_level.txt
simple_tg_md-0.1.1.dist-info/RECORD
