Metadata-Version: 2.2
Name: simple-tg-md
Version: 0.1.1
Summary: Простая библиотека для конвертирования в формат Telegram Markdown V2
Home-page: https://github.com/VKolebcev/simple-tg-md
Author: HalPerson
Author-email: vkolebcev@yandex.ru
License: MIT License
Project-URL: Homepage, https://github.com/VKolebcev/simple-tg-md
Project-URL: Bug Tracker, https://github.com/VKolebcev/simple-tg-md/issues
Requires-Python: >=3.9
License-File: LICENSE
Dynamic: author
Dynamic: author-email
Dynamic: home-page
Dynamic: requires-python
